bridgernadesigner/__init__.py
bridgernadesigner/classes.py
bridgernadesigner/errors.py
bridgernadesigner/main.py
bridgernadesigner/run.py
bridgernadesigner-0.1.1.dist-info/LICENSE
bridgernadesigner-0.1.1.dist-info/METADATA
bridgernadesigner-0.1.1.dist-info/WHEEL
bridgernadesigner-0.1.1.dist-info/entry_points.txt
bridgernadesigner-0.1.1.dist-info/top_level.txt
bridgernadesigner-0.1.1.dist-info/RECORD
