Metadata-Version: 2.1
Name: bridgernadesigner
Version: 0.1.1
Summary: Software package to design bridge RNAs as described by Durrant & Perry et al. 2024 and Perry et al. 2025
Home-page: https://github.com/hsulab-arc/BridgeRNADesigner
Author: Matt Durrant
Author-email: matthew@arcinstitute.org
License: MIT
License-File: LICENSE
Requires-Dist: biopython
Requires-Dist: click ==7.0
